SourceLink/Contributors.py
SourceLink/__init__.py
SourceLink-1.1.dist-info/LICENSE
SourceLink-1.1.dist-info/METADATA
SourceLink-1.1.dist-info/WHEEL
SourceLink-1.1.dist-info/top_level.txt
SourceLink-1.1.dist-info/RECORD
