Metadata-Version: 2.1
Name: SourceLink
Version: 1.1
Summary: Generate a file with the contribution list of your youtube video from a playlist. 📷
Home-page: https://github.com/ElHaban3ro/ConvTool
Author: ElHaban3ro
Author-email: habanferd@gmail.com
License: MIT
Keywords: python,playlists,youtube,content-creator
Classifier: Programming Language :: Python :: 3.9
Classifier: Programming Language :: Python :: 3.10
License-File: LICENSE
Requires-Dist: requests
